mcp_mathematics/__init__.py
mcp_mathematics/__main__.py
mcp_mathematics/calculator.py
mcp_mathematics-2.3.1.dist-info/METADATA
mcp_mathematics-2.3.1.dist-info/WHEEL
mcp_mathematics-2.3.1.dist-info/entry_points.txt
mcp_mathematics-2.3.1.dist-info/licenses/LICENSE
mcp_mathematics-2.3.1.dist-info/RECORD
