Metadata-Version: 2.4
Name: mcp-mathematics
Version: 2.3.1
Summary: Production-ready MCP server built with FastMCP v2 for comprehensive mathematical operations, providing 52 advanced functions, 158 unit conversions, and enterprise-grade security
Project-URL: Homepage, https://github.com/SHSharkar/MCP-Mathematics
Project-URL: Source, https://github.com/SHSharkar/MCP-Mathematics
Project-URL: Repository, https://github.com/SHSharkar/MCP-Mathematics
Project-URL: Issues, https://github.com/SHSharkar/MCP-Mathematics/issues
Project-URL: Documentation, https://github.com/SHSharkar/MCP-Mathematics#readme
Author-email: "Md. Sazzad Hossain Sharkar" <md@szd.sh>
License: MIT
License-File: LICENSE
Keywords: ai,api,assistant,calculator,chatgpt,claude,computation,converter,finance,formula,gpt,llm,math,mathematics,mcp,python,scientific,solver,tool,unit-conversion
Classifier: Development Status :: 5 - Production/Stable
Classifier: Intended Audience :: Developers
Classifier: License :: OSI Approved :: MIT License
Classifier: Programming Language :: Python :: 3
Classifier: Programming Language :: Python :: 3.10
Classifier: Programming Language :: Python :: 3.11
Classifier: Programming Language :: Python :: 3.12
Classifier: Programming Language :: Python :: 3.13
Classifier: Topic :: Scientific/Engineering :: Mathematics
Classifier: Topic :: Software Development :: Libraries :: Python Modules
Requires-Python: >=3.10
Requires-Dist: fastmcp>=0.1.0
Requires-Dist: mcp>=1.4.1
